scrapy_twostage
